odoo10_addon_account_invoice_tax_required-10.0.1.0.1-py2.7-nspkg.pth
odoo/addons/account_invoice_tax_required/README.rst
odoo/addons/account_invoice_tax_required/__init__.py
odoo/addons/account_invoice_tax_required/__manifest__.py
odoo/addons/account_invoice_tax_required/i18n/account_invoice_tax_require.pot
odoo/addons/account_invoice_tax_required/i18n/ar.po
odoo/addons/account_invoice_tax_required/i18n/bg.po
odoo/addons/account_invoice_tax_required/i18n/bs.po
odoo/addons/account_invoice_tax_required/i18n/ca.po
odoo/addons/account_invoice_tax_required/i18n/cs.po
odoo/addons/account_invoice_tax_required/i18n/de.po
odoo/addons/account_invoice_tax_required/i18n/el_GR.po
odoo/addons/account_invoice_tax_required/i18n/en_GB.po
odoo/addons/account_invoice_tax_required/i18n/es.po
odoo/addons/account_invoice_tax_required/i18n/es_CR.po
odoo/addons/account_invoice_tax_required/i18n/es_EC.po
odoo/addons/account_invoice_tax_required/i18n/es_MX.po
odoo/addons/account_invoice_tax_required/i18n/et.po
odoo/addons/account_invoice_tax_required/i18n/fi.po
odoo/addons/account_invoice_tax_required/i18n/fr.po
odoo/addons/account_invoice_tax_required/i18n/fr_CA.po
odoo/addons/account_invoice_tax_required/i18n/fr_CH.po
odoo/addons/account_invoice_tax_required/i18n/gl.po
odoo/addons/account_invoice_tax_required/i18n/hr.po
odoo/addons/account_invoice_tax_required/i18n/hr_HR.po
odoo/addons/account_invoice_tax_required/i18n/hu.po
odoo/addons/account_invoice_tax_required/i18n/id.po
odoo/addons/account_invoice_tax_required/i18n/it.po
odoo/addons/account_invoice_tax_required/i18n/ja.po
odoo/addons/account_invoice_tax_required/i18n/lt.po
odoo/addons/account_invoice_tax_required/i18n/mk.po
odoo/addons/account_invoice_tax_required/i18n/mn.po
odoo/addons/account_invoice_tax_required/i18n/nb.po
odoo/addons/account_invoice_tax_required/i18n/nb_NO.po
odoo/addons/account_invoice_tax_required/i18n/nl.po
odoo/addons/account_invoice_tax_required/i18n/nl_BE.po
odoo10_addon_account_invoice_tax_required-10.0.1.0.1.dist-info/DESCRIPTION.rst
odoo10_addon_account_invoice_tax_required-10.0.1.0.1.dist-info/METADATA
odoo10_addon_account_invoice_tax_required-10.0.1.0.1.dist-info/RECORD
odoo10_addon_account_invoice_tax_required-10.0.1.0.1.dist-info/WHEEL
odoo10_addon_account_invoice_tax_required-10.0.1.0.1.dist-info/metadata.json
odoo10_addon_account_invoice_tax_required-10.0.1.0.1.dist-info/namespace_packages.txt
odoo10_addon_account_invoice_tax_required-10.0.1.0.1.dist-info/top_level.txt
